python_ci_cd_sample/__init__.py
python_ci_cd_sample/log.py
python_ci_cd_sample/py.typed
python_ci_cd_sample/reader.py
python_ci_cd_sample-0.1.11.dist-info/LICENSE
python_ci_cd_sample-0.1.11.dist-info/METADATA
python_ci_cd_sample-0.1.11.dist-info/WHEEL
python_ci_cd_sample-0.1.11.dist-info/top_level.txt
python_ci_cd_sample-0.1.11.dist-info/RECORD
